README.md
setup.cfg
setup.py
Flask_B3.egg-info/PKG-INFO
Flask_B3.egg-info/SOURCES.txt
Flask_B3.egg-info/dependency_links.txt
Flask_B3.egg-info/requires.txt
Flask_B3.egg-info/top_level.txt
Flask_B3.egg-info/zip-safe
b3/__init__.py