Metadata-Version: 1.1
Name: Flask-B3
Version: 0.0.7
Summary: B3 header access and propagation for Flask.
Home-page: https://github.com/rosgovuk/flask_b3
Author: David Carboni
Author-email: david@carboni.io
License: MIT
Keywords: logging,b3,distributed,tracing,zipkin
Platform: UNKNOWN
Classifier: Development Status :: 3 - Alpha
Classifier: Programming Language :: Python :: 2.7
Classifier: Programming Language :: Python :: 3.2
Classifier: Topic :: System :: Logging
Classifier: Topic :: Internet :: Log Analysis
Classifier: Intended Audience :: Developers
Classifier: Framework :: Flask
Classifier: License :: OSI Approved :: MIT License
